ether_addr.pyi
ether_addr.cpython-39-x86_64-linux-gnu.so
ether_addr-0.1.0.dist-info/LICENSE
ether_addr-0.1.0.dist-info/WHEEL
ether_addr-0.1.0.dist-info/RECORD
ether_addr-0.1.0.dist-info/METADATA
ether_addr-0.1.0.dist-info/top_level.txt
