Metadata-Version: 2.1
Name: ether-addr
Version: 0.1.0
Summary: 48 bit ethernet address
Author: skrab-sah
Author-email: skrab.sah@gmail.com
Classifier: Operating System :: POSIX :: Linux
Classifier: License :: OSI Approved :: MIT License
License-File: LICENSE
